rsoup-3.1.8.dist-info/METADATA
rsoup-3.1.8.dist-info/WHEEL
rsoup-3.1.8.dist-info/licenses/LICENSE
rsoup/__init__.py
rsoup/core.cpython-311-x86_64-linux-gnu.so
rsoup/core.pyi
rsoup/exceptions.py
rsoup/fetch_tables.py
rsoup/python/context_extractor.py
rsoup/python/models/__init__.py
rsoup/python/models/context.py
rsoup/python/models/html_table.py
rsoup/python/table_extractor.py
rsoup-3.1.8.dist-info/RECORD
